cloudflare_access_jwt/__init__.py
cloudflare_access_jwt/cloudflare_access_jwt.py
cloudflare_access_jwt/cloudflare_access_jwt_test.py
fastapi_cloudflare_access_jwt-0.1.1.dist-info/METADATA
fastapi_cloudflare_access_jwt-0.1.1.dist-info/WHEEL
fastapi_cloudflare_access_jwt-0.1.1.dist-info/licenses/LICENSE
fastapi_cloudflare_access_jwt-0.1.1.dist-info/RECORD
