Metadata-Version: 2.4
Name: fastapi-cloudflare-access-jwt
Version: 0.1.1
Summary: FastAPI middleware for Cloudflare Access JWT authentication
Project-URL: Homepage, https://github.com/aluxian/fastapi-cloudflare-access-jwt
Project-URL: Repository, https://github.com/aluxian/fastapi-cloudflare-access-jwt.git
Project-URL: Issues, https://github.com/aluxian/fastapi-cloudflare-access-jwt/issues
Project-URL: Changelog, https://github.com/aluxian/fastapi-cloudflare-access-jwt/releases
Author-email: Alexandru Rosianu <me@aluxian.com>
License-Expression: MIT
License-File: LICENSE
Keywords: authentication,cloudflare,fastapi,jwt,middleware
Classifier: Development Status :: 4 - Beta
Classifier: Framework :: FastAPI
Classifier: Intended Audience :: Developers
Classifier: License :: OSI Approved :: MIT License
Classifier: Operating System :: OS Independent
Classifier: Programming Language :: Python :: 3
Classifier: Programming Language :: Python :: 3.12
Classifier: Topic :: Internet :: WWW/HTTP :: WSGI :: Middleware
Classifier: Topic :: Security
Requires-Python: >=3.12
Requires-Dist: cryptography>=42.0.5
Requires-Dist: fastapi[standard]>=0.110.0
Requires-Dist: loguru>=0.7.2
Requires-Dist: pyjwt>=2.8.0
Requires-Dist: requests>=2.31.0
